LICENSE
MANIFEST.in
README.md
setup.py
jupyter_coder_server/__init__.py
jupyter_coder_server/__main__.py
jupyter_coder_server/cli.py
jupyter_coder_server/coder_server.py
jupyter_coder_server/filebrowser.py
jupyter_coder_server/utils.py
jupyter_coder_server/version.py
jupyter_coder_server.egg-info/PKG-INFO
jupyter_coder_server.egg-info/SOURCES.txt
jupyter_coder_server.egg-info/dependency_links.txt
jupyter_coder_server.egg-info/entry_points.txt
jupyter_coder_server.egg-info/requires.txt
jupyter_coder_server.egg-info/top_level.txt
jupyter_coder_server/icons/__init__.py
jupyter_coder_server/icons/filebrowser.svg
jupyter_coder_server/icons/vscode.svg
jupyter_coder_server/labextensions/install.json
jupyter_coder_server/labextensions/jupyter_coder_server.json
jupyter_coder_server/labextensions/package.json